flask_tus_ponthe.py
Flask_Tus_Ponthe-1.1.4.dist-info/LICENSE
Flask_Tus_Ponthe-1.1.4.dist-info/METADATA
Flask_Tus_Ponthe-1.1.4.dist-info/WHEEL
Flask_Tus_Ponthe-1.1.4.dist-info/top_level.txt
Flask_Tus_Ponthe-1.1.4.dist-info/RECORD
